pymermaid/MermaidMarkdown.py
pymermaid/__init__.py
pymermaid/mermaid_js.py
pymermaid-1.7.1.dist-info/METADATA
pymermaid-1.7.1.dist-info/WHEEL
pymermaid-1.7.1.dist-info/top_level.txt
pymermaid-1.7.1.dist-info/RECORD
